xia_engine_mysql/__init__.py
xia_engine_mysql/engine.cpython-311-darwin.so
xia_engine_mysql-0.1.12.dist-info/LICENSE.txt
xia_engine_mysql-0.1.12.dist-info/METADATA
xia_engine_mysql-0.1.12.dist-info/WHEEL
xia_engine_mysql-0.1.12.dist-info/top_level.txt
xia_engine_mysql-0.1.12.dist-info/RECORD
