Metadata-Version: 2.1
Name: xia-engine-mysql
Version: 0.1.12
Summary: UNKNOWN
Home-page: https://develop.x-i-a.com/docs/xia-engine-mysql/0.1.12/index.html
Author: X-I-A
Author-email: admin@x-i-a.com
License: UNKNOWN
Platform: UNKNOWN
Requires-Python: >=3.9
License-File: LICENSE.txt
Requires-Dist: pymysql
Requires-Dist: xia-engine
Requires-Dist: xia-engine-sql
